{
  "headers": {
    "content-type": "application/javascript",
    "referrer-policy": "strict-origin-when-cross-origin",
    "x-amz-cf-id": "PAeMPcpwoGlZvrDU5u1cEFECvHieXljsz14k3kM4W-rZqlrUjom2dg==",
    "cross-origin-resource-policy": "same-origin",
    "x-cache": "Hit from cloudfront",
    "age": "5790823",
    "x-frame-options": "DENY",
    "x-amz-replication-status": "COMPLETED",
    "date": "Thu, 04 Jan 2024 10:20:18 GMT",
    "cache-control": "public, max-age=31536000, immutable",
    "via": "http/2 edgeproxy-h",
    "cross-origin-opener-policy": "same-origin",
    "cross-origin-embedder-policy": "same-origin",
    "server-timing": "fetchSource;dur=24",
    "x-amz-version-id": "knCDNmE.xl6L3iWjAvpq_7DnU6z5nO2M",
    "x-content-type-options": "nosniff",
    "content-security-policy": "default-src 'none'; style-src 'unsafe-inline'; sandbox",
    "vary": "Accept-Encoding, Origin",
    "strict-transport-security": "max-age=63072000; includeSubDomains; preload",
    "x-amz-cf-pop": "AMS50-C1",
    "server": "deno/gcp-europe-west4",
    "x-amz-server-side-encryption": "AES256",
    "access-control-allow-origin": "*",
    "etag": "W/\"0b3de48a9fdc77a8f8c6813ecca7461f\"",
    "last-modified": "Fri, 27 Oct 2023 15:58:52 GMT"
  },
  "url": "https://deno.land/x/postgresjs@v3.4.2/polyfills.js",
  "now": {
    "secs_since_epoch": 1710154440,
    "nanos_since_epoch": 26126261
  }
}